up2b2.py
up2b2-0.1.0.dist-info/LICENSE
up2b2-0.1.0.dist-info/METADATA
up2b2-0.1.0.dist-info/WHEEL
up2b2-0.1.0.dist-info/top_level.txt
up2b2-0.1.0.dist-info/RECORD
