Metadata-Version: 2.1
Name: up2b2
Version: 0.1.0
Summary: Save uploaded pictures in Backblaze B2.
Home-page: https://github.com/sapicd/up2b2
Author: staugur
Author-email: me@tcw.im
License: Apache 2.0
License-File: LICENSE
Requires-Dist: b2sdk (>=1.21.0)
